better/__init__.py
better/configparser.py
better/multiprocessing/__init__.py
better/multiprocessing/_exceptions.py
better/multiprocessing/_mplogging.py
better/multiprocessing/_poolmanager.py
better/threading/__init__.py
better/threading/_tfor.py
better/threading/_threads.py
betterpy-0.5.0.dist-info/LICENSE
betterpy-0.5.0.dist-info/METADATA
betterpy-0.5.0.dist-info/WHEEL
betterpy-0.5.0.dist-info/top_level.txt
betterpy-0.5.0.dist-info/RECORD
