Metadata-Version: 2.1
Name: betterpy
Version: 0.5.0
Summary: Extend packages include additional desired features
Home-page: https://github.com/Kieran-Bacon/Better
Author: Kieran Bacon
Author-email: Kieran.Bacon@outlook.com
License: UNKNOWN
Platform: UNKNOWN
Classifier: Programming Language :: Python :: 3
Classifier: License :: OSI Approved :: MIT License
